{"_t":"TaoTie.ConfigActor","Remarks":"测试子弹","Type":3,"Abilities":["Test_Bullet"],"Common":{"_t":"TaoTie.ConfigActorCommon","Height":0.1,"Scale":1,"ModelHeight":0.1,"ModelRadius":0.1,"NearFocusOffsetHeight":0.5},"Model":{"_t":"TaoTie.ConfigSingletonModel"},"Trigger":{"_t":"TaoTie.ConfigTrigger","ConcernType":1,"TriggerFlag":2,"CheckType":1,"Offset":{"x":0.0,"y":0.0,"z":0.0},"ConfigShape":{"_t":"TaoTie.ConfigSphereShape","Radius":0.2},"StartCheckTime":0,"CheckInterval":0,"CheckCount":-1,"TriggerInterval":0,"TriggerCount":4294967295,"TotalTriggerCount":4294967295,"LifeTime":-1,"ApplyEachModel":true},"Move":{"_t":"TaoTie.ConfigMove","Agent":{"_t":"TaoTie.ConfigSimpleMove"},"DefaultStrategy":{"_t":"TaoTie.ConfigBulletMove","Speed":10,"MaxSpeed":100000,"MinSpeed":0,"AnglerVelocity":{"_t":"TaoTie.ZeroValue"},"Acceleration":{"_t":"TaoTie.SingleValue","Value":0},"AccelerationTime":0,"Delay":0}}}