{"_t":"TaoTie.ConfigFsmTable","Layers":[{"_t":"TaoTie.ConfigFsmTableLayer","Name":"Base Layer","FsmStates":[{"_t":"TaoTie.ConfigFsmTableState","Name":"Hide","Clip":{"_t":"_UnityEngineObject","_ut":"UnityEngine.AnimationClip","_GUID":"12bf35c415f578c46bb1bfd6ece63c06"},"Data":{"_t":"TaoTie.StateData","IsDynamic":false,"PoseID":0,"CanMove":false,"CanTurn":false,"CanJump":false,"IsJump":false,"ShowWeapon":false,"UseRagDoll":false,"EffectBySpeed":false}},{"_t":"TaoTie.ConfigFsmTableState","Name":"Show","Clip":{"_t":"_UnityEngineObject","_ut":"UnityEngine.AnimationClip","_GUID":"e03d92092b00c5e4c969ac9484f03fd4"},"Data":{"_t":"TaoTie.StateData","IsDynamic":false,"PoseID":0,"CanMove":false,"CanTurn":false,"CanJump":false,"IsJump":false,"ShowWeapon":false,"UseRagDoll":false,"EffectBySpeed":false}}],"DataTable":{"_Length":[2,2],"_Array":[{"_t":"TaoTie.ConfigFsmTableItem","FromState":"Hide","ToState":"Hide"},{"_t":"TaoTie.ConfigFsmTableItem","FromState":"Show","ToState":"Hide","Transitions":[{"_t":"TaoTie.ConfigTransition","FromState":"Show","ToState":"Hide","ToStateTime":0,"FadeDuration":0.01,"CanTransitionToSelf":false,"InteractionSource":0,"OrderedInteraction":false,"Conditions":[{"_t":"TaoTie.ConfigConditionByDataBool","Value":false,"Key":"ShowWeapon","Mode":0}]}]},{"_t":"TaoTie.ConfigFsmTableItem","FromState":"Hide","ToState":"Show","Transitions":[{"_t":"TaoTie.ConfigTransition","FromState":"Hide","ToState":"Show","ToStateTime":0,"FadeDuration":0.01,"CanTransitionToSelf":false,"InteractionSource":0,"OrderedInteraction":false,"Conditions":[{"_t":"TaoTie.ConfigConditionByDataBool","Value":true,"Key":"ShowWeapon","Mode":0}]}]},{"_t":"TaoTie.ConfigFsmTableItem","FromState":"Show","ToState":"Show"}]}}]}